optmentorwidgets/__init__.py
optmentorwidgets/_frontend.py
optmentorwidgets/_version.py
optmentorwidgets/magic.py
optmentorwidgets/widget.py
optmentorwidgets/labextension/package.json
optmentorwidgets/labextension/static/122.64f5234e2d7734a30c2f.js
optmentorwidgets/labextension/static/25.90b70f7afda27c2332a4.js
optmentorwidgets/labextension/static/353.538cdd026a3c55d37e25.js
optmentorwidgets/labextension/static/406.90b70f7afda27c2332a4.js
optmentorwidgets/labextension/static/421.c901a3eef451f6e48264.js
optmentorwidgets/labextension/static/463.2a0fa89596602553e0bd.js
optmentorwidgets/labextension/static/491.4156648a595815c03b25.js
optmentorwidgets/labextension/static/509.1fed556bffb88545275d.js
optmentorwidgets/labextension/static/609.811e8c82e85d74d21b34.js
optmentorwidgets/labextension/static/747.7eb54661fc8a7364cc9d.js
optmentorwidgets/labextension/static/828.44ab5c9f04b45c3e3d8f.js
optmentorwidgets/labextension/static/885.4c45a84d31e1d06d5222.js
optmentorwidgets/labextension/static/remoteEntry.9bea44097997231924a2.js
optmentorwidgets/labextension/static/style.js
optmentorwidgets/labextension/static/third-party-licenses.json
optmentorwidgets/nbextension/extension.js
optmentorwidgets/nbextension/index.js
optmentorwidgets/nbextension/index.js.map
optmentorwidgets/nbextension/static/index.js.map
optmentorwidgets-0.2.8.data/data/etc/jupyter/nbconfig/notebook.d/optmentorwidgets.json
optmentorwidgets-0.2.8.data/data/share/jupyter/labextensions/jupyter-optmentorwidgets/install.json
optmentorwidgets-0.2.8.data/data/share/jupyter/labextensions/jupyter-optmentorwidgets/package.json
optmentorwidgets-0.2.8.data/data/share/jupyter/labextensions/jupyter-optmentorwidgets/static/122.64f5234e2d7734a30c2f.js
optmentorwidgets-0.2.8.data/data/share/jupyter/labextensions/jupyter-optmentorwidgets/static/25.90b70f7afda27c2332a4.js
optmentorwidgets-0.2.8.data/data/share/jupyter/labextensions/jupyter-optmentorwidgets/static/353.538cdd026a3c55d37e25.js
optmentorwidgets-0.2.8.dist-info/licenses/LICENSE.txt
optmentorwidgets-0.2.8.dist-info/METADATA
optmentorwidgets-0.2.8.dist-info/WHEEL
optmentorwidgets-0.2.8.dist-info/top_level.txt
optmentorwidgets-0.2.8.dist-info/RECORD
