Metadata-Version: 2.4
Name: optmentorwidgets
Version: 0.2.8
Summary: Jupyter Widgets for DIVE virtual learning environment.
Home-page: https://github.com/dive4dec/divewidgets
Author: Chung Chan
Author-email: chungc@alum.mit.edu
License: BSD
Platform: Linux
Platform: Mac OS X
Platform: Windows
Classifier: Intended Audience :: Education
Classifier: Intended Audience :: Developers
Classifier: Intended Audience :: Science/Research
Classifier: License :: OSI Approved :: BSD License
Classifier: Framework :: Jupyter
Classifier: Framework :: Jupyter :: JupyterLab
Classifier: Framework :: Jupyter :: JupyterLab :: 3
Classifier: Programming Language :: Python
Classifier: Programming Language :: Python :: 3.6
Classifier: Programming Language :: Python :: 3.7
Classifier: Programming Language :: Python :: 3.8
Classifier: Programming Language :: Python :: 3.9
Classifier: Programming Language :: Python :: 3.10
Classifier: Framework :: Jupyter
Requires-Python: >=3.6
License-File: LICENSE.txt
Requires-Dist: ipywidgets>=7.0.0
Provides-Extra: test
Requires-Dist: pytest>=4.6; extra == "test"
Requires-Dist: pytest-cov; extra == "test"
Requires-Dist: nbval; extra == "test"
Provides-Extra: docs
Requires-Dist: jupyter_sphinx; extra == "docs"
Requires-Dist: nbsphinx; extra == "docs"
Requires-Dist: nbsphinx-link; extra == "docs"
Requires-Dist: pytest_check_links; extra == "docs"
Requires-Dist: pypandoc; extra == "docs"
Requires-Dist: recommonmark; extra == "docs"
Requires-Dist: sphinx>=1.5; extra == "docs"
Requires-Dist: sphinx_rtd_theme; extra == "docs"
Dynamic: license-file
